cloud_tqdm/__init__.py
cloud_tqdm/constants.py
cloud_tqdm/std.py
cloud_tqdm-0.0.2.dist-info/METADATA
cloud_tqdm-0.0.2.dist-info/WHEEL
cloud_tqdm-0.0.2.dist-info/top_level.txt
cloud_tqdm-0.0.2.dist-info/RECORD
