Metadata-Version: 2.1
Name: cloud-tqdm
Version: 0.0.2
Summary: Visualize the progress of a Python script on the web.
Home-page: https://github.com/shunyooo/cloud-tqdm
Author: shunyooo
Author-email: shunyo.kawamoto@gmail.com
License: Apache License 2.0
Keywords: progress,tqdm,cloud
Platform: UNKNOWN
Requires-Python: >=3.6
Requires-Dist: tqdm
